alation/__init__.py
alation/cli/__init__.py
alation/cli/main.py
alation/cli/command_modules/__init__.py
alation/cli/core/__init__.py
alation/cli/core/auth.py
alation_cli-0.0.1.dist-info/DESCRIPTION.rst
alation_cli-0.0.1.dist-info/METADATA
alation_cli-0.0.1.dist-info/RECORD
alation_cli-0.0.1.dist-info/WHEEL
alation_cli-0.0.1.dist-info/entry_points.txt
alation_cli-0.0.1.dist-info/metadata.json
alation_cli-0.0.1.dist-info/top_level.txt
